{
    "success": true,
    "message": "Bed List Found.",
    "items": [
        {
            "itemNo": 1,
            "itemId": "1",
            "itemName": "ICU",
            "itemRate": 0,
            "itemQty": 1,
            "totalAmount": 0,
            "discount": 0,
            "netAmount": 0,
            "serialNo": 1,
            "activeStatus": 0
        },
        {
            "itemNo": 2,
            "itemId": "2",
            "itemName": "Single Cabin",
            "itemRate": 0,
            "itemQty": 1,
            "totalAmount": 0,
            "discount": 0,
            "netAmount": 0,
            "serialNo": 1,
            "activeStatus": 1
        },
        {
            "itemNo": 3,
            "itemId": "3",
            "itemName": "Double Cabin",
            "itemRate": 0,
            "itemQty": 1,
            "totalAmount": 0,
            "discount": 0,
            "netAmount": 0,
            "serialNo": 2,
            "activeStatus": 1
        },
        {
            "itemNo": 4,
            "itemId": "4",
            "itemName": "Geriatric HDU",
            "itemRate": 0,
            "itemQty": 1,
            "totalAmount": 0,
            "discount": 0,
            "netAmount": 0,
            "serialNo": 2,
            "activeStatus": 0
        },
        {
            "itemNo": 5,
            "itemId": "5",
            "itemName": "CCC",
            "itemRate": 0,
            "itemQty": 1,
            "totalAmount": 0,
            "discount": 0,
            "netAmount": 0,
            "serialNo": 2,
            "activeStatus": 0
        },
        {
            "itemNo": 6,
            "itemId": "6",
            "itemName": "CCU",
            "itemRate": 0,
            "itemQty": 1,
            "totalAmount": 0,
            "discount": 0,
            "netAmount": 0,
            "serialNo": 3,
            "activeStatus": 1
        },
        {
            "itemNo": 7,
            "itemId": "7",
            "itemName": "M-HDU/S-HDU",
            "itemRate": 0,
            "itemQty": 1,
            "totalAmount": 0,
            "discount": 0,
            "netAmount": 0,
            "serialNo": 2,
            "activeStatus": 0
        },
        {
            "itemNo": 8,
            "itemId": "8",
            "itemName": "E & C",
            "itemRate": 0,
            "itemQty": 1,
            "totalAmount": 0,
            "discount": 0,
            "netAmount": 0,
            "serialNo": 2,
            "activeStatus": 0
        },
        {
            "itemNo": 9,
            "itemId": "9",
            "itemName": "PACU",
            "itemRate": 0,
            "itemQty": 1,
            "totalAmount": 0,
            "discount": 0,
            "netAmount": 0,
            "serialNo": 5,
            "activeStatus": 1
        },
        {
            "itemNo": 10,
            "itemId": "10",
            "itemName": "Ventilator",
            "itemRate": 0,
            "itemQty": 1,
            "totalAmount": 0,
            "discount": 0,
            "netAmount": 0,
            "serialNo": 2,
            "activeStatus": 0
        },
        {
            "itemNo": 11,
            "itemId": "11",
            "itemName": "CPU",
            "itemRate": 0,
            "itemQty": 1,
            "totalAmount": 0,
            "discount": 0,
            "netAmount": 0,
            "serialNo": 4,
            "activeStatus": 1
        },
        {
            "itemNo": 12,
            "itemId": "12",
            "itemName": "Burn ICU",
            "itemRate": 0,
            "itemQty": 1,
            "totalAmount": 0,
            "discount": 0,
            "netAmount": 0,
            "serialNo": 6,
            "activeStatus": 1
        },
        {
            "itemNo": 13,
            "itemId": "13",
            "itemName": "CVS ICU",
            "itemRate": 0,
            "itemQty": 1,
            "totalAmount": 0,
            "discount": 0,
            "netAmount": 0,
            "serialNo": 7,
            "activeStatus": 1
        },
        {
            "itemNo": 14,
            "itemId": "14",
            "itemName": "P. ICU",
            "itemRate": 0,
            "itemQty": 1,
            "totalAmount": 0,
            "discount": 0,
            "netAmount": 0,
            "serialNo": 8,
            "activeStatus": 1
        }
    ]
}